LICENSE
MANIFEST.in
README.rst
setup.cfg
setup.py
chartit/__init__.py
chartit/chartdata.py
chartit/charts.py
chartit/exceptions.py
chartit/utils.py
chartit/validation.py
chartit/highcharts/__init__.py
chartit/highcharts/hcoptions.py
chartit/static/chartit/js/chartloader.js
chartit/templatetags/__init__.py
chartit/templatetags/chartit.py
django_highchartit.egg-info/PKG-INFO
django_highchartit.egg-info/SOURCES.txt
django_highchartit.egg-info/dependency_links.txt
django_highchartit.egg-info/not-zip-safe
django_highchartit.egg-info/top_level.txt